testcontainers_python_influxdb/__init__.py
testcontainers_python_influxdb/influxdb1/__init__.py
testcontainers_python_influxdb/influxdb2/__init__.py
testcontainers_python_influxdb-0.2.2.dist-info/LICENSE
testcontainers_python_influxdb-0.2.2.dist-info/METADATA
testcontainers_python_influxdb-0.2.2.dist-info/WHEEL
testcontainers_python_influxdb-0.2.2.dist-info/RECORD
