Metadata-Version: 2.1
Name: testcontainers-python-influxdb
Version: 0.2.2
Summary: Brings InfluxDB in testcontainers-python (until PR #413 is merged)
License: Apache-2.0
Author: Luc Sorel-Giffo
Requires-Python: >=3.8,<4.0
Classifier: License :: OSI Approved :: Apache Software License
Classifier: Programming Language :: Python :: 3
Classifier: Programming Language :: Python :: 3.8
Classifier: Programming Language :: Python :: 3.9
Classifier: Programming Language :: Python :: 3.10
Classifier: Programming Language :: Python :: 3.11
Provides-Extra: influxdb1
Provides-Extra: influxdb2
Requires-Dist: influxdb (>=5.3.1,<6.0.0) ; extra == "influxdb1"
Requires-Dist: influxdb-client (>=1.39.0,<2.0.0) ; extra == "influxdb2"
Requires-Dist: testcontainers (>=3.7.1,<4.0.0)
